pyargu/__init__.py
pyargu/colors.py
pyargu/completion.py
pyargu/errors.py
pyargu/parser.py
pyargu/utils.py
pyargu/validators.py
pyargu-0.0.3.dist-info/METADATA
pyargu-0.0.3.dist-info/WHEEL
pyargu-0.0.3.dist-info/top_level.txt
pyargu-0.0.3.dist-info/RECORD
