Metadata-Version: 2.4
Name: pyargu
Version: 0.0.3
Summary: Parser argumen command-line dari nol: config, ENV, validator, dan completion
Author: Athallah Rajendra Putra Juniarto
Author-email: example@email.com
License: MIT
Classifier: Programming Language :: Python :: 3
Classifier: Topic :: Software Development :: Libraries
Classifier: Environment :: Console
Classifier: Operating System :: OS Independent
Requires-Python: >=3.8
Dynamic: author
Dynamic: author-email
Dynamic: classifier
Dynamic: description-content-type
Dynamic: license
Dynamic: requires-python
Dynamic: summary
